tabs_storage/__init__.py
tabs_storage/home.py
tabs_storage/io/__init__.py
tabs_storage/io/reader.py
tabs_storage/io/writer.py
tabs_storage/storage.py
tabs_storage-0.1.3.dist-info/WHEEL
tabs_storage-0.1.3.dist-info/METADATA
tabs_storage-0.1.3.dist-info/RECORD
